sfr_walt-0.1.0.dist-info/licenses/LICENSE.txt
walt/__init__.py
walt/cli.py
walt/config.py
walt/benchmarks/__init__.py
walt/benchmarks/vwa/__init__.py
walt/benchmarks/vwa/accounts_config.py
walt/benchmarks/vwa/aeval.py
walt/benchmarks/vwa/auto_login.py
walt/benchmarks/vwa/discover.py
walt/benchmarks/vwa/generate_test_configs.py
walt/benchmarks/wa/__init__.py
walt/benchmarks/wa/accounts_config.py
walt/benchmarks/wa/aeval.py
walt/benchmarks/wa/auto_login.py
walt/benchmarks/wa/discover.py
walt/benchmarks/wa/generate_test_configs.py
walt/browser_use/__init__.py
walt/browser_use/logging_config.py
walt/browser_use/utils.py
walt/browser_use/agent/gif.py
walt/browser_use/agent/prompts.py
walt/browser_use/agent/service.py
walt/browser_use/agent/views.py
walt/browser_use/agent/message_manager/service.py
walt/browser_use/agent/message_manager/utils.py
walt/browser_use/agent/message_manager/views.py
walt/browser_use/browser/browser.py
walt/browser_use/browser/context.py
walt/browser_use/browser/views.py
walt/browser_use/controller/service.py
walt/browser_use/controller/views.py
walt/browser_use/controller/registry/service.py
walt/browser_use/controller/registry/views.py
walt/browser_use/custom/__init__.py
walt/browser_use/custom/agent_zoo.py
walt/browser_use/custom/browser_context_zoo.py
walt/browser_use/custom/browser_zoo.py
walt/browser_use/custom/controller_zoo.py
walt/browser_use/custom/dom_element_zoo.py
walt/browser_use/custom/dom_service_zoo.py
walt/browser_use/custom/get_args.py
walt/browser_use/custom/knowledge.py
walt/browser_use/custom/message_manager_zoo.py
walt/browser_use/custom/navigation_utils.py
walt/browser_use/custom/trajectory_parser.py
walt/browser_use/custom/utils.py
walt/browser_use/custom/eval_envs/VWA.py
walt/browser_use/custom/eval_envs/WA.py
walt/browser_use/custom/eval_envs/actions.py
walt/browser_use/custom/eval_envs/utils.py
walt/browser_use/custom/evaluators/__init__.py
walt/browser_use/custom/evaluators/vwa/__init__.py
walt/browser_use/custom/evaluators/vwa/constants.py
sfr_walt-0.1.0.dist-info/METADATA
sfr_walt-0.1.0.dist-info/WHEEL
sfr_walt-0.1.0.dist-info/entry_points.txt
sfr_walt-0.1.0.dist-info/top_level.txt
sfr_walt-0.1.0.dist-info/RECORD
