Metadata-Version: 2.4
Name: sfr-walt
Version: 0.1.0
Summary: Web Agents that Learn Tools - Automatic tool discovery from websites
Author-email: Viraj Prabhu <viraj.prabhu@salesforce.com>
License: Apache-2.0
Project-URL: Homepage, https://github.com/salesforceairesearch/walt
Project-URL: Documentation, https://github.com/salesforceairesearch/walt#readme
Project-URL: Repository, https://github.com/salesforceairesearch/walt
Project-URL: Issues, https://github.com/salesforceairesearch/walt/issues
Keywords: web-agents,llm,automation,tool-discovery,browser-use
Classifier: Development Status :: 3 - Alpha
Classifier: Intended Audience :: Developers
Classifier: Intended Audience :: Science/Research
Classifier: License :: OSI Approved :: Apache Software License
Classifier: Programming Language :: Python :: 3
Classifier: Programming Language :: Python :: 3.11
Classifier: Topic :: Scientific/Engineering :: Artificial Intelligence
Requires-Python: >=3.11
License-File: LICENSE.txt
Requires-Dist: playwright>=1.40.0
Requires-Dist: patchright>=1.0.0
Requires-Dist: langchain>=0.1.0
Requires-Dist: langchain-openai>=0.0.5
Requires-Dist: langchain-anthropic>=0.1.0
Requires-Dist: pydantic>=2.0.0
Requires-Dist: pydantic-settings>=2.0.0
Requires-Dist: typer>=0.9.0
Requires-Dist: rich>=13.0.0
Requires-Dist: aiofiles>=23.0.0
Requires-Dist: python-dotenv>=1.0.0
Requires-Dist: markdownify>=0.11.0
Requires-Dist: requests>=2.31.0
Requires-Dist: numpy>=1.24.0
Requires-Dist: sentence-transformers>=2.2.0
Requires-Dist: pyyaml>=6.0.0
Requires-Dist: faiss-cpu>=1.7.4
Requires-Dist: posthog>=3.0.0
Requires-Dist: beautifulsoup4>=4.9.0
Requires-Dist: lxml>=4.9.0
Requires-Dist: boto3>=1.28.0
Requires-Dist: langchain-google-genai>=2.1.12
Requires-Dist: langchain-aws>=0.2.35
Requires-Dist: ffmpy==0.6.3
Requires-Dist: langchain_community>=0.3.31
Provides-Extra: dev
Requires-Dist: pytest>=7.0.0; extra == "dev"
Requires-Dist: pytest-asyncio>=0.21.0; extra == "dev"
Requires-Dist: black>=23.0.0; extra == "dev"
Requires-Dist: ruff>=0.1.0; extra == "dev"
Requires-Dist: mypy>=1.0.0; extra == "dev"
Requires-Dist: torch>=2.0.0; extra == "dev"
Requires-Dist: transformers>=4.30.0; extra == "dev"
Requires-Dist: pillow>=10.0.0; extra == "dev"
Requires-Dist: nltk>=3.8.0; extra == "dev"
Requires-Dist: evaluate>=0.4.0; extra == "dev"
Requires-Dist: beartype>=0.22.2; extra == "dev"
Requires-Dist: aiolimiter>=1.0.0; extra == "dev"
Requires-Dist: cachetools>=5.0.0; extra == "dev"
Requires-Dist: tqdm>=4.65.0; extra == "dev"
Requires-Dist: openai>=1.0.0; extra == "dev"
Requires-Dist: scikit-image>=0.25.2; extra == "dev"
Requires-Dist: absl-py>=1.0.0; extra == "dev"
Requires-Dist: rouge-score>=0.1.2; extra == "dev"
Provides-Extra: recorder
Requires-Dist: uvicorn>=0.24.0; extra == "recorder"
Requires-Dist: fastapi>=0.104.0; extra == "recorder"
Provides-Extra: all
Requires-Dist: walt[dev,recorder]; extra == "all"
Dynamic: license-file
